LICENSE
README.rst
pyproject.toml
setup.py
bale/__init__.py
bale/__main__.py
bale/baleobject.py
bale/bot.py
bale/callbackquery.py
bale/chat.py
bale/chatmember.py
bale/chatphoto.py
bale/commands.py
bale/error.py
bale/helpers.py
bale/message.py
bale/state.py
bale/sticker.py
bale/update.py
bale/updater.py
bale/user.py
bale/version.py
bale/attachments/__init__.py
bale/attachments/animation.py
bale/attachments/audio.py
bale/attachments/contact.py
bale/attachments/document.py
bale/attachments/file.py
bale/attachments/input_file.py
bale/attachments/location.py
bale/attachments/photosize.py
bale/attachments/video.py
bale/payments/__init__.py
bale/payments/invoice.py
bale/payments/price.py
bale/payments/successful_payment.py
bale/request/__init__.py
bale/request/http.py
bale/request/params.py
bale/request/parser.py
bale/ui/__init__.py
bale/ui/inline_keyboard_button.py
bale/ui/inline_keyboard_markup.py
bale/ui/menu_keyboard_button.py
bale/ui/menu_keyboard_markup.py
bale/ui/reply_makrup.py
bale/ui/reply_markup_item.py
bale/utils/__init__.py
bale/utils/logging.py
bale/utils/request.py
bale/utils/types.py
python_bale_bot.egg-info/PKG-INFO
python_bale_bot.egg-info/SOURCES.txt
python_bale_bot.egg-info/dependency_links.txt
python_bale_bot.egg-info/requires.txt
python_bale_bot.egg-info/top_level.txt