Metadata-Version: 2.1
Name: python-bale-bot
Version: 2.5.0
Summary: An API wrapper for Bale written in Python
Home-page: https://github.com/python-bale-bot/python-bale-bot/
Download-URL: https://pypi.org/project/python-bale-bot/
Author: Kian Ahmadian
Author-email: devs@python-bale-bot.ir
License: LGPLv2
Project-URL: Documentation, https://docs.python-bale-bot.ir/en/stable/
Project-URL: Changelog, https://python-bale-bot.ir/changelog
Project-URL: Bug Tracker, https://github.com/python-bale-bot/python-bale-bot/issues
Project-URL: Source Code, https://github.com/python-bale-bot/python-bale-bot/
Project-URL: News, https://t.me/pbblib
Keywords: bale bale-bot framework bot
Platform: Windows
Requires-Python: >=3.8
License-File: LICENSE
Requires-Dist: aiohttp<3.9.2,>=3.6.0
Requires-Dist: asyncio~=3.4.3
Requires-Dist: setuptools~=69.0.3
Provides-Extra: docs
Requires-Dist: sphinx==7.2.6; extra == "docs"
Requires-Dist: sphinx-pypi-upload; extra == "docs"
Requires-Dist: sphinx-paramlinks==0.6.0; extra == "docs"
Requires-Dist: sphinxcontrib-mermaid==0.8.1; extra == "docs"
Requires-Dist: sphinx-copybutton==0.5.2; extra == "docs"
Requires-Dist: furo==2023.9.10; extra == "docs"
Requires-Dist: sphinx-inline-tabs==2023.4.21; extra == "docs"
